{
    "resourceType": "ValueSet",
    "id": "52b20417-0c95-4a93-9133-1db87042d802",
    "meta": {
        "versionId": "5",
        "lastUpdated": "2020-06-30T18:56:50.241+00:00"
    },
    "language": "pt-BR",
    "url": "http://www.saude.gov.br/fhir/r4/ValueSet/BRTipoAmostra-1.0",
    "version": "1.0",
    "name": "Tipo de Amostra de Exame",
    "status": "active",
    "experimental": false,
    "date": "2020-06-30T18:56:47.6561959+00:00",
    "publisher": "Ministério da Saúde do Brasil",
    "description": "Tipo da amostra de um exame ou teste.",
    "immutable": false,
    "compose": {
        "include": [
            {
                "system": "http://terminology.hl7.org/CodeSystem/v2-0487",
                "version": "*",
                "concept": [
                    {
                        "code": "FRS",
                        "display": "Fluido Respiratório"
                    },
                    {
                        "code": "LAVG",
                        "display": "Lavado Brônquico"
                    },
                    {
                        "code": "NSECR",
                        "display": "Secreção Nasal"
                    },
                    {
                        "code": "PLAS",
                        "display": "Plasma"
                    },
                    {
                        "code": "SPT",
                        "display": "Escarro"
                    },
                    {
                        "code": "TASP",
                        "display": "Aspirado Traqueal"
                    },
                    {
                        "code": "WB",
                        "display": "Sangue Total"
                    },
                    {
                        "code": "SER",
                        "display": "Soro"
                    },
                    {
                        "code": "SECRE",
                        "display": "Secreção Não Especificada"
                    },
                    {
                        "code": "ASP",
                        "display": "Aspirado Não Especificado"
                    },
                    {
                        "code": "SPUTIN",
                        "display": "Escarro induzido"
                    },
                    {
                        "code": "WASH",
                        "display": "Lavado"
                    },
                    {
                        "code": "CSF",
                        "display": "Líquor"
                    },
                    {
                        "code": "SAL",
                        "display": "Saliva"
                    },
                    {
                        "code": "UR",
                        "display": "Urina"
                    }
                ]
            },
            {
                "system": "http://www.saude.gov.br/fhir/r4/CodeSystem/BRTipoAmostraGAL",
                "version": "*"
            }
        ]
    }
}