{
  "resourceType": "StructureDefinition",
  "id": "d8303b8c-12e6-4e3b-8895-0d2de6c77262",
  "meta": {
    "versionId": "1",
    "lastUpdated": "2020-09-17T18:54:26.222+00:00"
  },
  "language": "pt-BR",
  "url": "http://www.saude.gov.br/fhir/r4/StructureDefinition/BREstadoResolucaoDiagnosticoProblema-1.0",
  "version": "1.0",
  "name": "BREstadoResolucaoDiagnosticoProblema",
  "title": "Estado da Resolução do Diagnóstico ou Problema",
  "status": "draft",
  "experimental": false,
  "date": "2020-09-17T18:54:32.5701295+00:00",
  "publisher": "Ministério da Saúde do Brasil",
  "fhirVersion": "4.0.1",
  "kind": "complex-type",
  "abstract": false,
  "context": [
    {
      "type": "element",
      "expression": "Condition"
    }
  ],
  "type": "Extension",
  "baseDefinition": "http://hl7.org/fhir/StructureDefinition/Extension",
  "derivation": "constraint",
  "differential": {
    "element": [
      {
        "id": "Extension",
        "path": "Extension",
        "short": "Estado da Resolução do Diagnóstico ou Problema",
        "max": "1",
        "isModifier": false
      },
      {
        "id": "Extension.url",
        "path": "Extension.url",
        "fixedUri": "http://www.saude.gov.br/fhir/r4/StructureDefinition/BREstadoResolucaoDiagnosticoProblema-1.0"
      },
      {
        "id": "Extension.value[x]",
        "path": "Extension.value[x]",
        "short": "Estado da Resolução",
        "min": 1,
        "type": [
          {
            "code": "CodeableConcept"
          }
        ],
        "binding": {
          "strength": "required",
          "description": "Estado da Resolução do Diagnóstico ou Problema",
          "valueSet": "http://www.saude.gov.br/fhir/r4/ValueSet/BREstadoResolucaoDiagnosticoProblema-1.0"
        }
      },
      {
        "id": "Extension.value[x].coding",
        "path": "Extension.value[x].coding",
        "min": 1,
        "max": "1"
      },
      {
        "id": "Extension.value[x].coding.system",
        "path": "Extension.value[x].coding.system",
        "min": 1
      },
      {
        "id": "Extension.value[x].coding.code",
        "path": "Extension.value[x].coding.code",
        "min": 1
      },
      {
        "id": "Extension.value[x].coding.display",
        "path": "Extension.value[x].coding.display",
        "max": "0"
      },
      {
        "id": "Extension.value[x].coding.userSelected",
        "path": "Extension.value[x].coding.userSelected",
        "max": "0"
      },
      {
        "id": "Extension.value[x].text",
        "path": "Extension.value[x].text",
        "max": "0"
      }
    ]
  }
}